README.md
setup.py
GInvDist.egg-info/PKG-INFO
GInvDist.egg-info/SOURCES.txt
GInvDist.egg-info/dependency_links.txt
GInvDist.egg-info/requires.txt
GInvDist.egg-info/top_level.txt
ginv/__init__.py
ginv/gb.py
ginv/ginv.py
ginv/janet.py
ginv/monom.py
ginv/poly.py
ginvdist.egg-info/PKG-INFO
ginvdist.egg-info/SOURCES.txt
ginvdist.egg-info/dependency_links.txt
ginvdist.egg-info/requires.txt
ginvdist.egg-info/top_level.txt